{
	"type": "minecraft:crafting_shaped",
	"pattern": [
		"2 2",
		"212",
		"232"
	],
	"key": {
		"1": {
			"item": "minecraft:bundle"
		},
		"2": {
			"item": "minecraft:command_block",
			"data": {
				"require": {
					"type": "kevlar_weave"
				}
			}
		},
		"3": {
			"item": "minecraft:netherite_chestplate",
			"data": {
				"require": {
					"type": "steel_chestplate"
				}
			}
		}
	},
	"result": {
		"item": "minecraft:iron_chestplate",
		"data": {
			"CustomModelData": 1,
			"type": "kevlar_vest",
			"Enchantments": [
				{
					"id": "minecraft:projectile_protection",
					"lvl": 4
				},
				{
					"id": "minecraft:protection",
					"lvl": 4
				},
				{
					"id": "minecraft:unbreaking",
					"lvl": 10
				}
			],
			"AttributeModifiers": [
				{
					"AttributeName": "generic.movement_speed",
					"Amount": -0.075,
					"Operation": 2,
					"Slot": "chest",
					"UUID": [
						105891,
						5819451,
						591805851,
						58191051
					]
				},
				{
					"AttributeName": "generic.armor",
					"Amount": 8,
					"Operation": 0,
					"Slot": "chest",
					"UUID":[
						589140194,
						591065930,
						495983295,
						1958196
					]
				}
			],
			"display": {
				"Name": "{\"italic\":false,\"color\":\"white\",\"text\":\"Kevlar Vest\"}",
				"Lore": [
					"[{\"text\":\"==========[ \",\"color\":\"dark_gray\",\"italic\":false},{\"text\":\"Stats\",\"color\":\"dark_aqua\",\"italic\":false},{\"text\":\" ]==========\",\"color\":\"dark_gray\",\"italic\":false}]",
					"{\"text\":\"● Inventory Space: 18\",\"color\":\"gray\",\"italic\":false}",
					"{\"text\":\"● Grants immunity to backstabs\",\"color\":\"gray\",\"italic\":false}"
				]
			}
		}
	}
}
